libpipe/__init__.py
libpipe/attrmap.py
libpipe/futils.py
libpipe/msutils.py
libpipe/settings.py
libpipe/tests/__init__.py
libpipe/tests/settings_test.toml
libpipe/tests/test_settings.py
libpipe/tests/test_worker.py
libpipe/tools/__init__.py
libpipe/tools/libnodes_bash.sh
libpipe/tools/nodetool.py
libpipe/worker.py
libpipe-0.4.dist-info/entry_points.txt
libpipe-0.4.dist-info/LICENSE
libpipe-0.4.dist-info/WHEEL
libpipe-0.4.dist-info/METADATA
libpipe-0.4.dist-info/RECORD
